[
  {
    "sector": [-1, 0],
    "floors": [
      {
        "0": [
          [-1, 1, 0, "floors"],
          [-1, 2, 0, "floors"],
          [-1, 3, 0, "floors"],
          [-1, 4, 0, "floors"],
          [-1, 5, 0, "floors"],
          [-1, 6, 0, "floors"],
          [-1, 7, 0, "floors"],
          [-1, 8, 0, "floors"],
          [-1, 9, 0, "floors"]
        ]
      }
    ]
  },
  {
    "sector": [-1, 1],
    "floors": [
      {
        "0": [
          [-1, 10, 0, "floors"],
          [-1, 11, 0, "floors"],
          [-1, 12, 0, "floors"],
          [-1, 13, 0, "floors"],
          [-1, 14, 0, "floors"],
          [-1, 15, 0, "floors"],
          [-1, 16, 0, "floors"],
          [-1, 17, 0, "floors"],
          [-1, 18, 0, "floors"],
          [-1, 19, 0, "floors"]
        ]
      }
    ]
  },
  {
    "sector": [0, 0],
    "floors": [
      {
        "0": [
          [0, 1, 0, "floors"],
          [0, 2, 0, "floors"],
          [0, 3, 0, "floors"],
          [0, 4, 0, "floors"],
          [0, 5, 0, "floors"],
          [0, 6, 0, "floors"],
          [0, 7, 0, "floors"],
          [0, 8, 0, "floors"],
          [0, 9, 0, "floors"],
          [1, 1, 0, "floors"],
          [1, 2, 0, "floors"],
          [1, 3, 0, "floors"],
          [1, 4, 0, "floors"],
          [1, 5, 0, "floors"],
          [1, 6, 0, "floors"],
          [1, 7, 0, "floors"],
          [1, 8, 0, "floors"],
          [1, 9, 0, "floors"],
          [2, 1, 0, "floors"],
          [2, 2, 0, "floors"],
          [2, 3, 0, "floors"],
          [2, 4, 0, "floors"],
          [2, 5, 0, "floors"],
          [2, 6, 0, "floors"],
          [2, 7, 0, "floors"],
          [2, 8, 0, "floors"],
          [2, 9, 0, "floors"],
          [3, 1, 0, "floors"],
          [3, 2, 0, "floors"],
          [3, 3, 0, "floors"],
          [3, 4, 0, "floors"],
          [3, 5, 0, "floors"],
          [3, 6, 0, "floors"],
          [3, 7, 0, "floors"],
          [3, 8, 0, "floors"],
          [3, 9, 0, "floors"],
          [4, 1, 0, "floors"],
          [4, 2, 0, "floors"],
          [4, 3, 0, "floors"],
          [4, 4, 0, "floors"],
          [4, 5, 0, "floors"],
          [4, 6, 0, "floors"],
          [4, 7, 0, "floors"],
          [4, 8, 0, "floors"],
          [4, 9, 0, "floors"],
          [5, 1, 0, "floors"],
          [5, 2, 0, "floors"],
          [5, 3, 0, "floors"],
          [5, 4, 0, "floors"],
          [5, 5, 0, "floors"],
          [5, 6, 0, "floors"],
          [5, 7, 0, "floors"],
          [5, 8, 0, "floors"],
          [5, 9, 0, "floors"],
          [6, 1, 0, "floors"],
          [6, 2, 0, "floors"],
          [6, 3, 0, "floors"],
          [6, 4, 0, "floors"],
          [6, 5, 0, "floors"],
          [6, 6, 0, "floors"],
          [6, 7, 0, "floors"],
          [6, 8, 0, "floors"],
          [6, 9, 0, "floors"],
          [7, 1, 0, "floors"],
          [7, 2, 0, "floors"],
          [7, 3, 0, "floors"],
          [7, 4, 0, "floors"],
          [7, 5, 0, "floors"],
          [7, 6, 0, "floors"],
          [7, 7, 0, "floors"],
          [7, 8, 0, "floors"],
          [7, 9, 0, "floors"],
          [8, 1, 0, "floors"],
          [8, 2, 0, "floors"],
          [8, 3, 0, "floors"],
          [8, 4, 0, "floors"],
          [8, 5, 0, "floors"],
          [8, 6, 0, "floors"],
          [8, 7, 0, "floors"],
          [8, 8, 0, "floors"],
          [8, 9, 0, "floors"],
          [9, 1, 0, "floors"],
          [9, 2, 0, "floors"],
          [9, 3, 0, "floors"],
          [9, 4, 0, "floors"],
          [9, 5, 0, "floors"],
          [9, 6, 0, "floors"],
          [9, 7, 0, "floors"],
          [9, 8, 0, "floors"],
          [9, 9, 0, "floors"]
        ]
      }
    ]
  },
  {
    "sector": [0, 1],
    "floors": [
      {
        "0": [
          [0, 10, 0, "floors"],
          [0, 11, 0, "floors"],
          [0, 12, 0, "floors"],
          [0, 13, 0, "floors"],
          [0, 14, 0, "floors"],
          [0, 15, 0, "floors"],
          [0, 16, 0, "floors"],
          [0, 17, 0, "floors"],
          [0, 18, 0, "floors"],
          [0, 19, 0, "floors"],
          [0, 10, 0, "floors"],
          [0, 11, 0, "floors"],
          [0, 12, 0, "floors"],
          [0, 13, 0, "floors"],
          [0, 14, 0, "floors"],
          [0, 15, 0, "floors"],
          [0, 16, 0, "floors"],
          [0, 17, 0, "floors"],
          [0, 18, 0, "floors"],
          [0, 19, 0, "floors"],
          [0, 10, 0, "floors"],
          [0, 11, 0, "floors"],
          [0, 12, 0, "floors"],
          [0, 13, 0, "floors"],
          [0, 14, 0, "floors"],
          [0, 15, 0, "floors"],
          [0, 16, 0, "floors"],
          [0, 17, 0, "floors"],
          [0, 18, 0, "floors"],
          [0, 19, 0, "floors"],
          [0, 10, 0, "floors"],
          [0, 11, 0, "floors"],
          [0, 12, 0, "floors"],
          [0, 13, 0, "floors"],
          [0, 14, 0, "floors"],
          [0, 15, 0, "floors"],
          [0, 16, 0, "floors"],
          [0, 17, 0, "floors"],
          [0, 18, 0, "floors"],
          [0, 19, 0, "floors"],
          [0, 10, 0, "floors"],
          [0, 11, 0, "floors"],
          [0, 12, 0, "floors"],
          [0, 13, 0, "floors"],
          [0, 14, 0, "floors"],
          [0, 15, 0, "floors"],
          [0, 16, 0, "floors"],
          [0, 17, 0, "floors"],
          [0, 18, 0, "floors"],
          [0, 19, 0, "floors"],
          [0, 10, 0, "floors"],
          [0, 11, 0, "floors"],
          [0, 12, 0, "floors"],
          [0, 13, 0, "floors"],
          [0, 14, 0, "floors"],
          [0, 15, 0, "floors"],
          [0, 16, 0, "floors"],
          [0, 17, 0, "floors"],
          [0, 18, 0, "floors"],
          [0, 19, 0, "floors"],
          [0, 10, 0, "floors"],
          [0, 11, 0, "floors"],
          [0, 12, 0, "floors"],
          [0, 13, 0, "floors"],
          [0, 14, 0, "floors"],
          [0, 15, 0, "floors"],
          [0, 16, 0, "floors"],
          [0, 17, 0, "floors"],
          [0, 18, 0, "floors"],
          [0, 19, 0, "floors"],
          [0, 10, 0, "floors"],
          [0, 11, 0, "floors"],
          [0, 12, 0, "floors"],
          [0, 13, 0, "floors"],
          [0, 14, 0, "floors"],
          [0, 15, 0, "floors"],
          [0, 16, 0, "floors"],
          [0, 17, 0, "floors"],
          [0, 18, 0, "floors"],
          [0, 19, 0, "floors"],
          [0, 10, 0, "floors"],
          [0, 11, 0, "floors"],
          [0, 12, 0, "floors"],
          [0, 13, 0, "floors"],
          [0, 14, 0, "floors"],
          [0, 15, 0, "floors"],
          [0, 16, 0, "floors"],
          [0, 17, 0, "floors"],
          [0, 18, 0, "floors"],
          [0, 19, 0, "floors"],
          [0, 10, 0, "floors"],
          [0, 11, 0, "floors"],
          [0, 12, 0, "floors"],
          [0, 13, 0, "floors"],
          [0, 14, 0, "floors"],
          [0, 15, 0, "floors"],
          [0, 16, 0, "floors"],
          [0, 17, 0, "floors"],
          [0, 18, 0, "floors"],
          [0, 19, 0, "floors"],
          [0, 10, 0, "floors"],
          [0, 11, 0, "floors"],
          [0, 12, 0, "floors"],
          [0, 13, 0, "floors"],
          [0, 14, 0, "floors"],
          [0, 15, 0, "floors"],
          [0, 16, 0, "floors"],
          [0, 17, 0, "floors"],
          [0, 18, 0, "floors"],
          [0, 19, 0, "floors"],
          [0, 10, 0, "floors"],
          [0, 11, 0, "floors"],
          [0, 12, 0, "floors"],
          [0, 13, 0, "floors"],
          [0, 14, 0, "floors"],
          [0, 15, 0, "floors"],
          [0, 16, 0, "floors"],
          [0, 17, 0, "floors"],
          [0, 18, 0, "floors"],
          [0, 19, 0, "floors"],
          [0, 10, 0, "floors"],
          [0, 11, 0, "floors"],
          [0, 12, 0, "floors"],
          [0, 13, 0, "floors"],
          [0, 14, 0, "floors"],
          [0, 15, 0, "floors"],
          [0, 16, 0, "floors"],
          [0, 17, 0, "floors"],
          [0, 18, 0, "floors"],
          [0, 19, 0, "floors"],
          [0, 10, 0, "floors"],
          [0, 11, 0, "floors"],
          [0, 12, 0, "floors"],
          [0, 13, 0, "floors"],
          [0, 14, 0, "floors"],
          [0, 15, 0, "floors"],
          [0, 16, 0, "floors"],
          [0, 17, 0, "floors"],
          [0, 18, 0, "floors"],
          [0, 19, 0, "floors"],
          [0, 10, 0, "floors"],
          [0, 11, 0, "floors"],
          [0, 12, 0, "floors"],
          [0, 13, 0, "floors"],
          [0, 14, 0, "floors"],
          [0, 15, 0, "floors"],
          [0, 16, 0, "floors"],
          [0, 17, 0, "floors"],
          [0, 18, 0, "floors"],
          [0, 19, 0, "floors"],
          [0, 10, 0, "floors"],
          [0, 11, 0, "floors"],
          [0, 12, 0, "floors"],
          [0, 13, 0, "floors"],
          [0, 14, 0, "floors"],
          [0, 15, 0, "floors"],
          [0, 16, 0, "floors"],
          [0, 17, 0, "floors"],
          [0, 18, 0, "floors"],
          [0, 19, 0, "floors"],
          [1, 10, 0, "floors"],
          [1, 11, 0, "floors"],
          [2, 10, 0, "floors"],
          [3, 10, 0, "floors"],
          [4, 10, 0, "floors"],
          [5, 10, 0, "floors"],
          [6, 10, 0, "floors"],
          [7, 10, 0, "floors"],
          [8, 10, 0, "floors"],
          [9, 10, 0, "floors"],
          [0, 11, 0, "floors"],
          [1, 11, 0, "floors"],
          [2, 11, 0, "floors"],
          [3, 11, 0, "floors"],
          [4, 11, 0, "floors"],
          [5, 11, 0, "floors"],
          [6, 11, 0, "floors"],
          [7, 11, 0, "floors"],
          [8, 11, 0, "floors"],
          [9, 11, 0, "floors"],
          [10, 11, 0, "floors"],
          [0, 12, 0, "floors"],
          [1, 12, 0, "floors"],
          [2, 12, 0, "floors"],
          [3, 12, 0, "floors"],
          [4, 12, 0, "floors"],
          [5, 12, 0, "floors"],
          [6, 12, 0, "floors"],
          [7, 12, 0, "floors"],
          [8, 12, 0, "floors"],
          [9, 12, 0, "floors"],
          [0, 13, 0, "floors"],
          [1, 13, 0, "floors"],
          [2, 13, 0, "floors"],
          [3, 13, 0, "floors"],
          [4, 13, 0, "floors"],
          [5, 13, 0, "floors"],
          [6, 13, 0, "floors"],
          [7, 13, 0, "floors"],
          [8, 13, 0, "floors"],
          [9, 13, 0, "floors"],
          [0, 14, 0, "floors"],
          [1, 14, 0, "floors"],
          [2, 14, 0, "floors"],
          [3, 14, 0, "floors"],
          [4, 14, 0, "floors"],
          [5, 14, 0, "floors"],
          [6, 14, 0, "floors"],
          [7, 14, 0, "floors"],
          [8, 14, 0, "floors"],
          [9, 14, 0, "floors"],
          [0, 15, 0, "floors"],
          [1, 15, 0, "floors"],
          [2, 15, 0, "floors"],
          [3, 15, 0, "floors"],
          [4, 15, 0, "floors"],
          [5, 15, 0, "floors"],
          [6, 15, 0, "floors"],
          [7, 15, 0, "floors"],
          [8, 15, 0, "floors"],
          [9, 15, 0, "floors"],
          [0, 16, 0, "floors"],
          [1, 16, 0, "floors"],
          [2, 16, 0, "floors"],
          [3, 16, 0, "floors"],
          [4, 16, 0, "floors"],
          [5, 16, 0, "floors"],
          [6, 16, 0, "floors"],
          [7, 16, 0, "floors"],
          [8, 16, 0, "floors"],
          [9, 16, 0, "floors"],
          [0, 17, 0, "floors"],
          [1, 17, 0, "floors"],
          [2, 17, 0, "floors"],
          [3, 17, 0, "floors"],
          [4, 17, 0, "floors"],
          [5, 17, 0, "floors"],
          [6, 17, 0, "floors"],
          [7, 17, 0, "floors"],
          [8, 17, 0, "floors"],
          [9, 17, 0, "floors"],
          [0, 18, 0, "floors"],
          [1, 18, 0, "floors"],
          [2, 18, 0, "floors"],
          [3, 18, 0, "floors"],
          [4, 18, 0, "floors"],
          [5, 18, 0, "floors"],
          [6, 18, 0, "floors"],
          [7, 18, 0, "floors"],
          [8, 18, 0, "floors"],
          [9, 18, 0, "floors"],
          [0, 19, 0, "floors"],
          [1, 19, 0, "floors"],
          [2, 19, 0, "floors"],
          [3, 19, 0, "floors"],
          [4, 19, 0, "floors"],
          [5, 19, 0, "floors"],
          [6, 19, 0, "floors"],
          [7, 19, 0, "floors"],
          [8, 19, 0, "floors"],
          [9, 19, 0, "floors"]
        ]
      }
    ]
  },
  {
    "sector": [1, 0],
    "floors": [
      {
        "0": [
          [10, 1, 0, "floors"],
          [10, 2, 0, "floors"],
          [10, 3, 0, "floors"],
          [10, 4, 0, "floors"],
          [10, 5, 0, "floors"],
          [10, 6, 0, "floors"],
          [10, 7, 0, "floors"],
          [10, 8, 0, "floors"],
          [10, 9, 0, "floors"],
          [11, 1, 0, "floors"],
          [11, 2, 0, "floors"],
          [11, 3, 0, "floors"],
          [11, 4, 0, "floors"],
          [11, 5, 0, "floors"],
          [11, 6, 0, "floors"],
          [11, 7, 0, "floors"],
          [11, 8, 0, "floors"],
          [11, 9, 0, "floors"],
          [12, 1, 0, "floors"],
          [12, 2, 0, "floors"],
          [12, 3, 0, "floors"],
          [12, 4, 0, "floors"],
          [12, 5, 0, "floors"],
          [12, 6, 0, "floors"],
          [12, 7, 0, "floors"],
          [12, 8, 0, "floors"],
          [12, 9, 0, "floors"],
          [13, 1, 0, "floors"],
          [13, 2, 0, "floors"],
          [13, 3, 0, "floors"],
          [13, 4, 0, "floors"],
          [13, 5, 0, "floors"],
          [13, 6, 0, "floors"],
          [13, 7, 0, "floors"],
          [13, 8, 0, "floors"],
          [13, 9, 0, "floors"],
          [14, 1, 0, "floors"],
          [14, 2, 0, "floors"],
          [14, 3, 0, "floors"],
          [14, 4, 0, "floors"],
          [14, 5, 0, "floors"],
          [14, 6, 0, "floors"],
          [14, 7, 0, "floors"],
          [14, 8, 0, "floors"],
          [14, 9, 0, "floors"],
          [15, 1, 0, "floors"],
          [15, 2, 0, "floors"],
          [15, 3, 0, "floors"],
          [15, 4, 0, "floors"],
          [15, 5, 0, "floors"],
          [15, 6, 0, "floors"],
          [15, 7, 0, "floors"],
          [15, 8, 0, "floors"],
          [15, 9, 0, "floors"]
        ]
      }
    ]
  },
  {
    "sector": [1, 1],
    "floors": [{"0": [
      [10, 10, 0, "floors"], 
      [11, 10, 0, "floors"],
      [12, 10, 0, "floors"],
      [13, 10, 0, "floors"],
      [14, 10, 0, "floors"],
      [15, 10, 0, "floors"],
      
      [10, 11, 0, "floors"],
      [11, 11, 0, "floors"],
      [12, 11, 0, "floors"],
      [13, 11, 0, "floors"],
      [14, 11, 0, "floors"],
      [15, 11, 0, "floors"],
      
      [10, 12, 0, "floors"],
      [11, 12, 0, "floors"],
      [12, 12, 0, "floors"],
      [13, 12, 0, "floors"],
      [14, 12, 0, "floors"],
      [15, 12, 0, "floors"],
      
      [10, 13, 0, "floors"],
      [11, 13, 0, "floors"],
      [12, 13, 0, "floors"],
      [13, 13, 0, "floors"],
      [14, 13, 0, "floors"],
      [15, 13, 0, "floors"],
      
      [10, 14, 0, "floors"],
      [11, 14, 0, "floors"],
      [12, 14, 0, "floors"],
      [13, 14, 0, "floors"],
      [14, 14, 0, "floors"],
      [15, 14, 0, "floors"],
      
      [10, 15, 0, "floors"],
      [11, 15, 0, "floors"],
      [12, 15, 0, "floors"],
      [13, 15, 0, "floors"],
      [14, 15, 0, "floors"],
      [15, 15, 0, "floors"],
      
      [10, 16, 0, "floors"],
      [11, 16, 0, "floors"],
      [12, 16, 0, "floors"],
      [13, 16, 0, "floors"],
      [14, 16, 0, "floors"],
      [15, 16, 0, "floors"],
      
      [10, 17, 0, "floors"],
      [11, 17, 0, "floors"],
      [12, 17, 0, "floors"],
      [13, 17, 0, "floors"],
      [14, 17, 0, "floors"],
      [15, 17, 0, "floors"],
      
      [10, 18, 0, "floors"],
      [11, 18, 0, "floors"],
      [12, 18, 0, "floors"],
      [13, 18, 0, "floors"],
      [14, 18, 0, "floors"],
      [15, 18, 0, "floors"],
      
      [10, 19, 0, "floors"],
      [11, 19, 0, "floors"],
      [12, 19, 0, "floors"],
      [13, 19, 0, "floors"],
      [14, 19, 0, "floors"],
      [15, 19, 0, "floors"]

    ]}]
  }
]